tjcommon/__init__.py
tjcommon/utilities.cpython-312-x86_64-linux-gnu.so
tjcommon-1.0.1.dist-info/METADATA
tjcommon-1.0.1.dist-info/WHEEL
tjcommon-1.0.1.dist-info/top_level.txt
tjcommon-1.0.1.dist-info/RECORD
