Metadata-Version: 2.4
Name: tjcommon
Version: 1.0.1
Summary: Common algorithm for all products of Tai-Ji Control
Author-email: kkzhang <kkzhang3@hotmail.com>
Requires-Python: >=3.5
Requires-Dist: cython
Requires-Dist: numpy
Requires-Dist: scipy
